setup.py
dalga/__init__.py
dalga.egg-info/PKG-INFO
dalga.egg-info/SOURCES.txt
dalga.egg-info/dependency_links.txt
dalga.egg-info/requires.txt
dalga.egg-info/top_level.txt