Metadata-Version: 1.1
Name: dalga
Version: 0.1.0
Summary: Dalga client in Python
Home-page: http://github.com/cenkalti/python-dalga
Author: Cenk Altı
Author-email: cenkalti@gmail.com
License: UNKNOWN
Platform: UNKNOWN
Classifier: Development Status :: 4 - Beta
Classifier: Intended Audience :: Developers
Classifier: License :: OSI Approved :: MIT License
Classifier: Operating System :: OS Independent
Classifier: Programming Language :: Python
Classifier: Programming Language :: Python :: 2.7
Classifier: Topic :: Software Development :: Object Brokering
Classifier: Topic :: System :: Distributed Computing
